llmarizer/__init__.py
llmarizer/summarizer.py
llummarizer-0.0.1.dist-info/licenses/LICENSE
llummarizer-0.0.1.dist-info/METADATA
llummarizer-0.0.1.dist-info/WHEEL
llummarizer-0.0.1.dist-info/top_level.txt
llummarizer-0.0.1.dist-info/RECORD
