Metadata-Version: 2.4
Name: llummarizer
Version: 0.0.1
Summary: A python package for summarizing text using an LLM model.
Author-email: Nick Baughman <nbaugh1@gmail.com>
License-Expression: MIT
Classifier: Programming Language :: Python :: 3
Classifier: Operating System :: OS Independent
Requires-Python: >=3.12
License-File: LICENSE
Dynamic: license-file
